pystackreg/__init__.py
pystackreg/conftest.py
pystackreg/pystackreg.py
pystackreg/turboreg.cp37-win32.pyd
pystackreg/version.py
pystackreg/util/__init__.py
pystackreg-0.2.8.dist-info/AUTHORS.rst
pystackreg-0.2.8.dist-info/LICENSE.txt
pystackreg-0.2.8.dist-info/METADATA
pystackreg-0.2.8.dist-info/WHEEL
pystackreg-0.2.8.dist-info/top_level.txt
pystackreg-0.2.8.dist-info/RECORD
