Metadata-Version: 2.1
Name: pystackreg
Version: 0.2.8
Summary: Image registration tool (python implementation of the ImageJ/FIJI Plugin TurboReg/StackReg)
Home-page: https://github.com/glichtner/pystackreg
Author: Gregor Lichtner (python/C++ port);TurboReg Author: Philippe Thévenaz, Biomedical Imaging Group,Swiss Federal Institute of Technology Lausanne
Classifier: Development Status :: 5 - Production/Stable
Classifier: Intended Audience :: Science/Research
Classifier: License :: Free To Use But Restricted
Classifier: Operating System :: Microsoft :: Windows
Classifier: Operating System :: Unix
Classifier: Operating System :: POSIX
Classifier: Programming Language :: C++
Classifier: Programming Language :: Python
Classifier: Programming Language :: Python :: 3.7
Classifier: Programming Language :: Python :: 3.8
Classifier: Programming Language :: Python :: 3.9
Classifier: Programming Language :: Python :: 3.10
Classifier: Programming Language :: Python :: 3.11
Classifier: Programming Language :: Python :: 3.12
Classifier: Topic :: Scientific/Engineering :: Image Processing
Classifier: Topic :: Utilities
License-File: LICENSE.txt
License-File: AUTHORS.rst
Requires-Dist: numpy
Requires-Dist: tqdm
